amm_geminiassist/__init__.py
amm_geminiassist/core.py
amm_geminiassist-0.1.2.dist-info/licenses/LICENSE
amm_geminiassist-0.1.2.dist-info/METADATA
amm_geminiassist-0.1.2.dist-info/WHEEL
amm_geminiassist-0.1.2.dist-info/top_level.txt
amm_geminiassist-0.1.2.dist-info/RECORD
