Metadata-Version: 2.4
Name: amm_geminiassist
Version: 0.1.2
Summary: Gemini-powered AI helper functions for Flask web apps
Author-email: Albin Mathew <albinmmathew@gmail.com>
License: MIT
Requires-Python: >=3.8
License-File: LICENSE
Requires-Dist: google-generativeai>=0.6.0
Dynamic: license-file
